oci_lego_exec
