Metadata-Version: 2.1
Name: oci-lego-exec
Version: 0.1.1
Summary: Oracle Cloud infrastructure DNS Authenticator script for LEGO
Home-page: https://github.com/ITD27M01/oci-lego-exec
Author: itd27m01
Author-email: igortiunov@gmail.com
License: MIT
Platform: UNKNOWN
Classifier: Programming Language :: Python :: 3
Classifier: Programming Language :: Python :: 3.8
Classifier: License :: OSI Approved :: MIT License
Classifier: Intended Audience :: System Administrators
Classifier: Environment :: Plugins
Classifier: Operating System :: OS Independent
Classifier: Topic :: Security
Classifier: Topic :: System :: Networking
Classifier: Topic :: System :: Systems Administration
Classifier: Topic :: Utilities
